FlaskKuozhanWendangHuizong/README.md
FlaskKuozhanWendangHuizong/__init__.py
FlaskKuozhanWendangHuizong/__main__.py
FlaskKuozhanWendangHuizong/file.epub
FlaskKuozhanWendangHuizong/index.html
FlaskKuozhanWendangHuizong/css/__init__.py
FlaskKuozhanWendangHuizong/css/annotations.css
FlaskKuozhanWendangHuizong/css/main.css
FlaskKuozhanWendangHuizong/css/normalize.css
FlaskKuozhanWendangHuizong/css/popup.css
FlaskKuozhanWendangHuizong/font/__init__.py
FlaskKuozhanWendangHuizong/font/fontello.eot
FlaskKuozhanWendangHuizong/font/fontello.svg
FlaskKuozhanWendangHuizong/font/fontello.ttf
FlaskKuozhanWendangHuizong/font/fontello.woff
FlaskKuozhanWendangHuizong/img/__init__.py
FlaskKuozhanWendangHuizong/img/annotator-glyph-sprite.png
FlaskKuozhanWendangHuizong/img/annotator-icon-sprite.png
FlaskKuozhanWendangHuizong/img/apple-touch-icon.png
FlaskKuozhanWendangHuizong/img/cancelfullscreen.png
FlaskKuozhanWendangHuizong/img/close.png
FlaskKuozhanWendangHuizong/img/fullscreen.png
FlaskKuozhanWendangHuizong/img/loader.gif
FlaskKuozhanWendangHuizong/img/menu-icon.png
FlaskKuozhanWendangHuizong/img/save.png
FlaskKuozhanWendangHuizong/img/saved.png
FlaskKuozhanWendangHuizong/img/settings-s.png
FlaskKuozhanWendangHuizong/img/settings.png
FlaskKuozhanWendangHuizong/img/star.png
FlaskKuozhanWendangHuizong/js/__init__.py
FlaskKuozhanWendangHuizong/js/epub.js
FlaskKuozhanWendangHuizong/js/epub.min.js
FlaskKuozhanWendangHuizong/js/epub.min.map
FlaskKuozhanWendangHuizong/js/hooks.min.js
FlaskKuozhanWendangHuizong/js/hooks.min.map
FlaskKuozhanWendangHuizong/js/reader.js
FlaskKuozhanWendangHuizong/js/reader.js.map
FlaskKuozhanWendangHuizong/js/reader.min.js
FlaskKuozhanWendangHuizong/js/reader.min.map
FlaskKuozhanWendangHuizong/js/hooks/__init__.py
FlaskKuozhanWendangHuizong/js/hooks/extensions/__init__.py
FlaskKuozhanWendangHuizong/js/hooks/extensions/highlight.js
FlaskKuozhanWendangHuizong/js/libs/__init__.py
FlaskKuozhanWendangHuizong/js/libs/jquery.min.js
flask_kuozhan_wendang_huizong-2024.3.1.0.dist-info/METADATA
flask_kuozhan_wendang_huizong-2024.3.1.0.dist-info/WHEEL
flask_kuozhan_wendang_huizong-2024.3.1.0.dist-info/entry_points.txt
flask_kuozhan_wendang_huizong-2024.3.1.0.dist-info/top_level.txt
flask_kuozhan_wendang_huizong-2024.3.1.0.dist-info/RECORD
